{
  "file": "determine-sentence-type.dart",
  "functions": [
    {
      "name": "main",
      "source": "void main() {\n  List<String> spam = [\n    \"hi there, how are you today?\",\n    \"I'd like to present to you the washing machine 9001.\",\n    \"You have been nominated to win one of these!\",\n    \"Just make sure you don't break it\"\n  ];\n\n  for (var s in spam) {\n    print('$s -> ${sentenceType(s)}');\n  }\n}",
      "assembly": "Dump of assembler code for function main:\n   0x000000000008a20c <+0>:\tpush   rbp\n   0x000000000008a20d <+1>:\tmov    rbp,rsp\n   0x000000000008a210 <+4>:\tsub    rsp,0x30\n   0x000000000008a214 <+8>:\tcmp    rsp,QWORD PTR [r14+0x38]\n   0x000000000008a218 <+12>:\tjbe    0x8a413 <main+519>\n   0x000000000008a21e <+18>:\tmov    rbx,QWORD PTR [r14+0x70]\n   0x000000000008a222 <+22>:\tmov    r10d,0x8\n   0x000000000008a228 <+28>:\tcall   0x84d08 <stub _iso_stub_AllocateArrayStub>\n   0x000000000008a22d <+33>:\tmov    rbx,rax\n   0x000000000008a230 <+36>:\tmov    QWORD PTR [rbp-0x18],rbx\n   0x000000000008a234 <+40>:\tmov    r11,QWORD PTR [r15+0x17f7]\n   0x000000000008a23b <+47>:\tmov    QWORD PTR [rbx+0x17],r11\n   0x000000000008a23f <+51>:\tmov    r11,QWORD PTR [r15+0x17ff]\n   0x000000000008a246 <+58>:\tmov    QWORD PTR [rbx+0x1f],r11\n   0x000000000008a24a <+62>:\tmov    r11,QWORD PTR [r15+0x1807]\n   0x000000000008a251 <+69>:\tmov    QWORD PTR [rbx+0x27],r11\n   0x000000000008a255 <+73>:\tmov    r11,QWORD PTR [r15+0x180f]\n   0x000000000008a25c <+80>:\tmov    QWORD PTR [rbx+0x2f],r11\n   0x000000000008a260 <+84>:\txor    eax,eax\n   0x000000000008a262 <+86>:\tcmp    rsp,QWORD PTR [r14+0x38]\n   0x000000000008a266 <+90>:\tjbe    0x8a41f <main+531>\n   0x000000000008a26c <+96>:\tcmp    rax,0x4\n   0x000000000008a270 <+100>:\tjge    0x8a40a <main+510>\n   0x000000000008a276 <+106>:\tmov    rsi,QWORD PTR [rbx+rax*8+0x17]\n   0x000000000008a27b <+111>:\tmov    QWORD PTR [rbp-0x10],rsi\n   0x000000000008a27f <+115>:\tmov    rdi,rax\n   0x000000000008a282 <+118>:\tadd    rdi,0x1\n   0x000000000008a286 <+122>:\tmov    QWORD PTR [rbp-0x8],rdi\n   0x000000000008a28a <+126>:\tcmp    rsi,QWORD PTR [r14+0x70]\n   0x000000000008a28e <+130>:\tjne    0x8a2cf <main+195>\n   0x000000000008a294 <+136>:\tmov    rax,rsi\n   0x000000000008a297 <+139>:\tmov    rdx,QWORD PTR [r14+0x70]\n   0x000000000008a29b <+143>:\tmov    rcx,QWORD PTR [r14+0x70]\n   0x000000000008a29f <+147>:\ttest   al,0x1\n   0x000000000008a2a1 <+149>:\tmov    esi,0x3c\n   0x000000000008a2a6 <+154>:\tje     0x8a2ae <main+162>\n   0x000000000008a2a8 <+156>:\tmov    esi,DWORD PTR [rax-0x1]\n   0x000000000008a2ab <+159>:\tshr    esi,0xc\n   0x000000000008a2ae <+162>:\tsub    rsi,0x5e\n   0x000000000008a2b2 <+166>:\tcmp    rsi,0x1\n   0x000000000008a2b6 <+170>:\tjbe    0x8a2cf <main+195>\n   0x000000000008a2bc <+176>:\tmov    rbx,QWORD PTR [r15+0x107]\n   0x000000000008a2c3 <+183>:\tmov    r9,QWORD PTR [r15+0x1817]\n   0x000000000008a2ca <+190>:\tcall   0x8ad10 <assert type is String>\n   0x000000000008a2cf <+195>:\tmov    rax,QWORD PTR [rbp-0x10]\n   0x000000000008a2d3 <+199>:\tmov    rbx,QWORD PTR [r14+0x70]\n   0x000000000008a2d7 <+203>:\tmov    r10d,0x6\n   0x000000000008a2dd <+209>:\tcall   0x84d08 <stub _iso_stub_AllocateArrayStub>\n   0x000000000008a2e2 <+214>:\tmov    rcx,rax\n   0x000000000008a2e5 <+217>:\tmov    rax,QWORD PTR [rbp-0x10]\n   0x000000000008a2e9 <+221>:\tmov    QWORD PTR [rbp-0x20],rcx\n   0x000000000008a2ed <+225>:\tmov    QWORD PTR [rcx+0x17],rax\n   0x000000000008a2f1 <+229>:\tmov    r11,QWORD PTR [r15+0x1827]\n   0x000000000008a2f8 <+236>:\tmov    QWORD PTR [rcx+0x1f],r11\n   0x000000000008a2fc <+240>:\tmov    rdx,QWORD PTR [rax+0x7]\n   0x000000000008a300 <+244>:\tsar    rdx,1\n   0x000000000008a303 <+247>:\tsub    rdx,0x1\n   0x000000000008a307 <+251>:\tmov    rbx,rdx\n   0x000000000008a30a <+254>:\tadd    rbx,rbx\n   0x000000000008a30d <+257>:\tmov    QWORD PTR [rsp+0x8],rax\n   0x000000000008a312 <+262>:\tmov    QWORD PTR [rsp],rbx\n   0x000000000008a316 <+266>:\tcall   0x5b73c <_StringBase.[]>\n   0x000000000008a31b <+271>:\tmov    QWORD PTR [rbp-0x10],rax\n   0x000000000008a31f <+275>:\tmov    ecx,DWORD PTR [rax-0x1]\n   0x000000000008a322 <+278>:\tshr    ecx,0xc\n   0x000000000008a325 <+281>:\tmov    QWORD PTR [rsp+0x8],rax\n   0x000000000008a32a <+286>:\tmov    r11,QWORD PTR [r15+0x4e7]\n   0x000000000008a331 <+293>:\tmov    QWORD PTR [rsp],r11\n   0x000000000008a335 <+297>:\tmov    rax,QWORD PTR [r14+0x58]\n   0x000000000008a339 <+301>:\tcall   QWORD PTR [rax+rcx*8]\n   0x000000000008a33c <+304>:\ttest   al,0x10\n   0x000000000008a33e <+306>:\tjne    0x8a350 <main+324>\n   0x000000000008a344 <+312>:\tmov    rax,QWORD PTR [r15+0x182f]\n   0x000000000008a34b <+319>:\tjmp    0x8a3c1 <main+437>\n   0x000000000008a350 <+324>:\tmov    rax,QWORD PTR [rbp-0x10]\n   0x000000000008a354 <+328>:\tmov    ecx,DWORD PTR [rax-0x1]\n   0x000000000008a357 <+331>:\tshr    ecx,0xc\n   0x000000000008a35a <+334>:\tmov    QWORD PTR [rsp+0x8],rax\n   0x000000000008a35f <+339>:\tmov    r11,QWORD PTR [r15+0x1837]\n   0x000000000008a366 <+346>:\tmov    QWORD PTR [rsp],r11\n   0x000000000008a36a <+350>:\tmov    rax,QWORD PTR [r14+0x58]\n   0x000000000008a36e <+354>:\tcall   QWORD PTR [rax+rcx*8]\n   0x000000000008a371 <+357>:\ttest   al,0x10\n   0x000000000008a373 <+359>:\tjne    0x8a385 <main+377>\n   0x000000000008a379 <+365>:\tmov    rax,QWORD PTR [r15+0x183f]\n   0x000000000008a380 <+372>:\tjmp    0x8a3c1 <main+437>\n   0x000000000008a385 <+377>:\tmov    rax,QWORD PTR [rbp-0x10]\n   0x000000000008a389 <+381>:\tmov    ecx,DWORD PTR [rax-0x1]\n   0x000000000008a38c <+384>:\tshr    ecx,0xc\n   0x000000000008a38f <+387>:\tmov    QWORD PTR [rsp+0x8],rax\n   0x000000000008a394 <+392>:\tmov    r11,QWORD PTR [r15+0xbf]\n   0x000000000008a39b <+399>:\tmov    QWORD PTR [rsp],r11\n   0x000000000008a39f <+403>:\tmov    rax,QWORD PTR [r14+0x58]\n   0x000000000008a3a3 <+407>:\tcall   QWORD PTR [rax+rcx*8]\n   0x000000000008a3a6 <+410>:\ttest   al,0x10\n   0x000000000008a3a8 <+412>:\tjne    0x8a3ba <main+430>\n   0x000000000008a3ae <+418>:\tmov    rax,QWORD PTR [r15+0x1847]\n   0x000000000008a3b5 <+425>:\tjmp    0x8a3c1 <main+437>\n   0x000000000008a3ba <+430>:\tmov    rax,QWORD PTR [r15+0x184f]\n   0x000000000008a3c1 <+437>:\tmov    rdx,QWORD PTR [rbp-0x20]\n   0x000000000008a3c5 <+441>:\tlea    r13,[rdx+0x27]\n   0x000000000008a3c9 <+445>:\tmov    QWORD PTR [r13+0x0],rax\n   0x000000000008a3cd <+449>:\ttest   al,0x1\n   0x000000000008a3cf <+451>:\tje     0x8a3e8 <main+476>\n   0x000000000008a3d1 <+453>:\tmov    r11b,BYTE PTR [rdx-0x1]\n   0x000000000008a3d5 <+457>:\tshr    r11d,0x2\n   0x000000000008a3d9 <+461>:\tand    r11d,DWORD PTR [r14+0x40]\n   0x000000000008a3dd <+465>:\ttest   BYTE PTR [rax-0x1],r11b\n   0x000000000008a3e1 <+469>:\tje     0x8a3e8 <main+476>\n   0x000000000008a3e3 <+471>:\tcall   0x83320 <stub _iso_stub_ArrayWriteBarrierStub>\n   0x000000000008a3e8 <+476>:\tmov    r11,QWORD PTR [rbp-0x20]\n   0x000000000008a3ec <+480>:\tmov    QWORD PTR [rsp],r11\n   0x000000000008a3f0 <+484>:\tcall   0x5b448 <_StringBase._interpolate>\n   0x000000000008a3f5 <+489>:\tmov    rdi,rax\n   0x000000000008a3f8 <+492>:\tcall   0x8a42c <printToConsole>\n   0x000000000008a3fd <+497>:\tmov    rax,QWORD PTR [rbp-0x8]\n   0x000000000008a401 <+501>:\tmov    rbx,QWORD PTR [rbp-0x18]\n   0x000000000008a405 <+505>:\tjmp    0x8a262 <main+86>\n   0x000000000008a40a <+510>:\tmov    rax,QWORD PTR [r14+0x70]\n   0x000000000008a40e <+514>:\tmov    rsp,rbp\n   0x000000000008a411 <+517>:\tpop    rbp\n   0x000000000008a412 <+518>:\tret\n   0x000000000008a413 <+519>:\tcall   QWORD PTR [r14+0x230]\n   0x000000000008a41a <+526>:\tjmp    0x8a21e <main+18>\n   0x000000000008a41f <+531>:\tcall   QWORD PTR [r14+0x230]\n   0x000000000008a426 <+538>:\tjmp    0x8a26c <main+96>\nEnd of assembler dump.\n"
    }
  ]
}